GaiaClusterFit/GCA.py
GaiaClusterFit/__init__.py
GaiaClusterFit/evalmetric.py
GaiaClusterFit-0.0.9.dist-info/METADATA
GaiaClusterFit-0.0.9.dist-info/WHEEL
GaiaClusterFit-0.0.9.dist-info/top_level.txt
GaiaClusterFit-0.0.9.dist-info/RECORD
