Metadata-Version: 2.1
Name: GaiaClusterFit
Version: 0.0.9
Summary: Matching gaia clustered stars to known clusters
Author: Levi van Es
Author-email: <levi2234@hotmail.com>
